candas/__init__.py
candas/database.py
candas/dataframe.py
candas/metadata.py
CANdas-2.0.2.dist-info/LICENSE
CANdas-2.0.2.dist-info/METADATA
CANdas-2.0.2.dist-info/WHEEL
CANdas-2.0.2.dist-info/top_level.txt
CANdas-2.0.2.dist-info/RECORD
