Metadata-Version: 2.1
Name: CANdas
Version: 2.0.2
Summary: Manage CAN Data elegantly.
Home-page: https://gitlab.com/lionsracing/candas
Author: Julian Wagenschütz
Author-email: julian@wagenschuetz.com
License: UNKNOWN
Platform: UNKNOWN
Classifier: Development Status :: 5 - Production/Stable
Classifier: Intended Audience :: Science/Research
Classifier: License :: OSI Approved :: MIT License
Classifier: Programming Language :: Python :: 3
Classifier: Programming Language :: Python :: 3.5
Classifier: Programming Language :: Python :: 3.6
Classifier: Programming Language :: Python :: 3.7
Requires-Python: >=3.5
Requires-Dist: matplotlib
Requires-Dist: numpy
Requires-Dist: cantools
Requires-Dist: scipy
Requires-Dist: python-can
Requires-Dist: pandas
Provides-Extra: docs
Requires-Dist: sphinx ; extra == 'docs'
Requires-Dist: alabaster ; extra == 'docs'
Requires-Dist: m2r ; extra == 'docs'
Provides-Extra: sql
Requires-Dist: SQLAlchemy ; extra == 'sql'
Requires-Dist: mysqlclient ; extra == 'sql'
Provides-Extra: test
Requires-Dist: coverage ; extra == 'test'
